setup.py
framboise/__init__.py
framboise/chksum.py
framboise/framboise.py
framboise/opensubtitles.py
framboise/sorting.py
framboise/util.py
framboise.egg-info/PKG-INFO
framboise.egg-info/SOURCES.txt
framboise.egg-info/dependency_links.txt
framboise.egg-info/entry_points.txt
framboise.egg-info/not-zip-safe
framboise.egg-info/top_level.txt