Metadata-Version: 1.0
Name: framboise
Version: 0.2
Summary: Utility to download subtitles from opensubtitles.org
Home-page: https://github.com/luisguilherme/framboise
Author: Luis Guilherme Pereira
Author-email: dev@luisguilherme.net
License: MIT
Platform: UNKNOWN
